setup.cfg
setup.py
my_rada/__init__.py
my_rada/descriptors.py
my_rada/rada_consoles.py
my_rada/rada_databases.py
my_rada/rada_factories.py
my_rada/rada_metaclass.py
my_rada/rada_models.py
my_rada/utils.py
my_rada/verh_rada.py
my_rada.egg-info/PKG-INFO
my_rada.egg-info/SOURCES.txt
my_rada.egg-info/dependency_links.txt
my_rada.egg-info/entry_points.txt
my_rada.egg-info/not-zip-safe
my_rada.egg-info/top_level.txt