Metadata-Version: 1.0
Name: my-rada
Version: 0.2.dev0
Summary: My rada
Home-page: UNKNOWN
Author: Trush Vasyl
Author-email: vinclaw78@gmail.com
License: UNKNOWN
Keywords: Abstract fuctory
Platform: UNKNOWN
